{
  "accentColor": "{{appsmith.theme.colors.primaryColor}}",
  "animateLoading": true,
  "autoFocus": false,
  "borderRadius": "{{appsmith.theme.borderRadius.appBorderRadius}}",
  "bottomRow": 34,
  "boxShadow": "none",
  "defaultText": "{{ Table_Users.selectedRow?.Limit || '' }}",
  "dynamicBindingPathList": [
    {
      "key": "accentColor"
    },
    {
      "key": "borderRadius"
    },
    {
      "key": "defaultText"
    }
  ],
  "dynamicHeight": "FIXED",
  "dynamicTriggerPathList": [],
  "iconAlign": "left",
  "inputType": "TEXT",
  "isDisabled": false,
  "isLoading": false,
  "isRequired": false,
  "isVisible": true,
  "key": "hhjjtqqvky",
  "label": "Approval Limit",
  "labelAlignment": "left",
  "labelPosition": "Left",
  "labelStyle": "",
  "labelTextSize": "0.875rem",
  "labelWidth": "9",
  "leftColumn": 41,
  "maxDynamicHeight": 9000,
  "minDynamicHeight": 4,
  "minWidth": 450,
  "mobileBottomRow": 34,
  "mobileLeftColumn": 41,
  "mobileRightColumn": 61,
  "mobileTopRow": 27,
  "needsErrorInfo": false,
  "parentColumnSpace": 12.15460205078125,
  "parentId": "xn0byl7sht",
  "parentRowSpace": 10,
  "renderMode": "CANVAS",
  "resetOnSubmit": true,
  "responsiveBehavior": "fill",
  "rightColumn": 61,
  "showStepArrows": false,
  "topRow": 27,
  "type": "INPUT_WIDGET_V2",
  "version": 2,
  "widgetId": "ebomfxvg5s",
  "widgetName": "Input_ApprovalLimit"
}